LICENSE
MANIFEST.in
README.md
requirements.txt
setup.cfg
setup.py
pytado/__init__.py
pytado/__main__.py
pytado/interface.py
pytado.egg-info/PKG-INFO
pytado.egg-info/SOURCES.txt
pytado.egg-info/dependency_links.txt
pytado.egg-info/entry_points.txt
pytado.egg-info/not-zip-safe
pytado.egg-info/top_level.txt