Metadata-Version: 1.1
Name: pytado
Version: 1.0.3
Summary: Python library for communicating with the Tado Smart Thermostat API.
Home-page: https://github.com/gazzer82/pytado
Author: Gareth Jeanne
Author-email: contact@garethjeanne.co.uk
License: GPL3
Download-URL: https://github.com/gazzr82/pytado/tarball/1.0.3
Keywords: pytado
Platform: UNKNOWN
Classifier: Development Status :: 3 - Alpha
Classifier: Topic :: Home Automation
Classifier: Intended Audience :: Developers
Classifier: License :: OSI Approved :: GNU General Public License v3 (GPLv3)
Classifier: Natural Language :: English
Classifier: Programming Language :: Python :: 3
Classifier: Programming Language :: Python :: 3.3
Classifier: Programming Language :: Python :: 3.5
